expman/__init__.py
expman/experiment.py
expman/loggers/__init__.py
expman/loggers/json_logger.py
expman/loggers/logger.py
expman/loggers/stdout_logger.py
expman/loggers/wandb_logger.py
expman/plotters/__init__.py
expman/plotters/line_plotter.py
expman/plotters/plotter.py
expman-0.0.5.dist-info/METADATA
expman-0.0.5.dist-info/RECORD
expman-0.0.5.dist-info/WHEEL
expman-0.0.5.dist-info/top_level.txt
