Metadata-Version: 2.1
Name: expman
Version: 0.0.5
Summary: Experiment manager.
Home-page: https://github.com/vzhong/expman
Author: Victor Zhong
Author-email: victor@victorzhong.com
License: MIT
Keywords: text nlp machine-learning
Platform: UNKNOWN
Classifier: Development Status :: 3 - Alpha
Classifier: Intended Audience :: Developers
Classifier: License :: OSI Approved :: MIT License
Classifier: Programming Language :: Python :: 3.5
Provides-Extra: dev
Provides-Extra: test
Requires-Dist: ujson
Provides-Extra: dev
Requires-Dist: check-manifest; extra == 'dev'
Requires-Dist: sphinx; extra == 'dev'
Requires-Dist: sphinx-rtd-theme; extra == 'dev'
Provides-Extra: test
Requires-Dist: coverage; extra == 'test'
Requires-Dist: nose; extra == 'test'
